sqlaudit/__init__.py
sqlaudit/_internals/__init__.py
sqlaudit/_internals/buffer.py
sqlaudit/_internals/logger.py
sqlaudit/_internals/models.py
sqlaudit/_internals/registry.py
sqlaudit/_internals/types.py
sqlaudit/_internals/utils.py
sqlaudit/config.py
sqlaudit/context.py
sqlaudit/decorators.py
sqlaudit/exceptions.py
sqlaudit/hooks.py
sqlaudit/process.py
sqlaudit/registry.py
sqlaudit/retrieval.py
sqlaudit/serializer.py
sqlaudit/types.py
sqlaudit-0.7.0.dist-info/METADATA
sqlaudit-0.7.0.dist-info/WHEEL
sqlaudit-0.7.0.dist-info/RECORD
