Metadata-Version: 2.4
Name: sqlaudit
Version: 0.7.0
Summary: SQLAlchemy extension that provides an easy way to track changes to your database models.
Author: Sander J. Bouwman
Requires-Python: >=3.13
Classifier: Programming Language :: Python :: 3
Classifier: Programming Language :: Python :: 3.13
Classifier: Programming Language :: Python :: 3.14
Requires-Dist: pydantic (>=2.11.5,<3.0.0)
Requires-Dist: sqlalchemy (>=2.0.41,<3.0.0)
Requires-Dist: tzlocal (>=5.3.1,<6.0.0)
Requires-Dist: uuid-utils (>=0.11.0,<0.12.0)
Project-URL: Changelog, https://github.com/SanderJBouwman/sqlaudit/releases
Project-URL: Issues, https://github.com/SanderJBouwman/sqlaudit/issues
Project-URL: Repository, https://github.com/SanderJBouwman/sqlaudit
